codesi/__init__.py
codesi/__main__.py
codesi/cli.py
codesi/exceptions.py
codesi/repl.py
codesi/runner.py
codesi/features/__init__.py
codesi/features/jaadu.py
codesi/features/samjho.py
codesi/features/timemachine.py
codesi/interpreter/__init__.py
codesi/interpreter/builtins.py
codesi/interpreter/interpreter.py
codesi/interpreter/runtime.py
codesi/lexer/__init__.py
codesi/lexer/lexer.py
codesi/lexer/tokens.py
codesi/parser/__init__.py
codesi/parser/ast_nodes.py
codesi/parser/parser.py
codesi-0.0.1.dist-info/licenses/LICENSE
codesi-0.0.1.dist-info/METADATA
codesi-0.0.1.dist-info/WHEEL
codesi-0.0.1.dist-info/entry_points.txt
codesi-0.0.1.dist-info/top_level.txt
codesi-0.0.1.dist-info/RECORD
