Metadata-Version: 2.4
Name: Codesi
Version: 0.0.1
Summary: First of its Kind Programming Language
Home-page: https://github.com/codesi-lang
Author: Rishaank Gupta
Author-email: Rishaank Gupta <site.rishaank@gmail.com>
License: MIT
Project-URL: Github, https://github.com/codesi-lang
Keywords: codesi,hinglish,hindi,programming
Classifier: Development Status :: 4 - Beta
Classifier: License :: OSI Approved :: MIT License
Classifier: Programming Language :: Python :: 3
Requires-Python: >=3.7
License-File: LICENSE
Dynamic: author
Dynamic: home-page
Dynamic: license-file
Dynamic: requires-python
